{"2020-6":[{"title":"Hello World","date":"2020-06-25T16:00:00.000Z","link":"/2020/06/26/HelloWorld/"},{"title":"Hexo博客定制--1.开始搭建","date":"2020-06-26T16:00:00.000Z","link":"/2020/06/27/Hexo博客定制--1.开始搭建/"},{"title":"Hexo博客定制--2.主题安装","date":"2020-06-27T16:00:00.000Z","link":"/2020/06/28/Hexo博客定制--2.主题安装/"},{"title":"Hexo博客定制--3.主题页面","date":"2020-06-28T16:00:00.000Z","link":"/2020/06/29/Hexo博客定制--3.主题页面/"},{"title":"Hexo博客定制--4.主题配置","date":"2020-06-29T16:00:00.000Z","link":"/2020/06/30/Hexo博客定制--4.主题配置/"}],"2020-7":[{"title":"python基础学习--计算机基础知识","date":"2020-06-30T16:00:00.000Z","link":"/2020/07/01/python基础学习--计算机基础/"},{"title":"python基础学习--python入门","date":"2020-07-01T16:00:00.000Z","link":"/2020/07/02/python基础学习--入门/"},{"title":"python基础学习--流程控制语句","date":"2020-07-02T16:00:00.000Z","link":"/2020/07/03/python基础学习--流程控制语句/"},{"title":"python基础学习--序列（1）","date":"2020-07-03T16:00:00.000Z","link":"/2020/07/04/python基础学习--序列（1）/"},{"title":"python基础学习--序列（2）","date":"2020-07-04T16:00:00.000Z","link":"/2020/07/05/python基础学习--序列（2）/"},{"title":"python基础学习--函数（1）","date":"2020-07-05T16:00:00.000Z","link":"/2020/07/06/python基础学习--函数(1)/"},{"title":"python基础学习--函数（2）","date":"2020-07-06T16:00:00.000Z","link":"/2020/07/07/python基础学习--函数(2)/"},{"title":"python基础学习--对象（1）","date":"2020-07-07T16:00:00.000Z","link":"/2020/07/08/python基础学习--对象(1)/"},{"title":"python基础学习--对象（2）","date":"2020-07-08T16:00:00.000Z","link":"/2020/07/09/python基础学习--对象（2）/"},{"title":"python基础学习--对象（3）","date":"2020-07-08T16:00:00.000Z","link":"/2020/07/09/python基础学习--对象（3）/"},{"title":"python基础学习--异常和文件（1）","date":"2020-07-09T16:00:00.000Z","link":"/2020/07/10/python基础学习--异常和文件（1）/"},{"title":"python基础学习--异常和文件（2）","date":"2020-07-09T16:00:00.000Z","link":"/2020/07/10/python基础学习--异常和文件（2）/"},{"title":"Linux系统管理--Linux简介","date":"2020-07-10T16:00:00.000Z","link":"/2020/07/11/Linux系统管理--Linux简介/"},{"title":"Linux系统管理--Linux安装","date":"2020-07-11T16:00:00.000Z","link":"/2020/07/12/Linux系统管理--Linux安装/"},{"title":"Linux系统管理--给初学者的建议","date":"2020-07-11T16:00:00.000Z","link":"/2020/07/12/Linux系统管理--给初学者的建议/"},{"title":"Linux系统管理--常用命令（1）","date":"2020-07-12T16:00:00.000Z","link":"/2020/07/13/Linux系统管理--常用命令  (1)/"},{"title":"Linux系统管理--常用命令（2）","date":"2020-07-14T16:00:00.000Z","link":"/2020/07/15/Linux系统管理--常用命令（2）/"},{"title":"Hexo博客定制--5.主题配置","date":"2020-07-19T16:00:00.000Z","link":"/2020/07/20/Hexo博客定制--5.主题配置/"},{"title":"Linux系统管理--常用命令（3）","date":"2020-07-22T16:00:00.000Z","link":"/2020/07/23/Linux系统管理--常用命令（3）/"}],"2020-9":[{"title":"Linux系统管理--常用命令（4）","date":"2020-09-15T16:00:00.000Z","link":"/2020/09/16/Linux系统管理--常用命令（4）/"},{"title":"Linux系统管理--vim编辑器","date":"2020-09-19T16:00:00.000Z","link":"/2020/09/20/Linux系统管理--vim编辑器/"},{"title":"Linux系统管理--软件包管理(1)","date":"2020-09-21T16:00:00.000Z","link":"/2020/09/22/Linux系统管理--软件包管理(1)/"}],"2020-10":[{"title":"Linux系统管理--软件包管理(2)","date":"2020-10-07T16:00:00.000Z","link":"/2020/10/08/Linux系统管理--软件包管理(2)/"},{"title":"Linux系统管理--软件包管理(3)","date":"2020-10-14T16:00:00.000Z","link":"/2020/10/15/Linux系统管理--软件包管理(3)/"},{"title":"Linux系统管理--用户管理(1)","date":"2020-10-16T16:00:00.000Z","link":"/2020/10/17/Linux系统管理--用户管理(1)/"}]}